gdb-stubs/FrameDecorator.pyi
gdb-stubs/FrameIterator.pyi
gdb-stubs/METADATA.toml
gdb-stubs/__init__.pyi
gdb-stubs/disassembler.pyi
gdb-stubs/events.pyi
gdb-stubs/missing_debug.pyi
gdb-stubs/missing_files.pyi
gdb-stubs/missing_objfile.pyi
gdb-stubs/printing.pyi
gdb-stubs/prompt.pyi
gdb-stubs/py.typed
gdb-stubs/types.pyi
gdb-stubs/unwinder.pyi
gdb-stubs/xmethod.pyi
gdb-stubs/dap/__init__.pyi
gdb-stubs/dap/breakpoint.pyi
gdb-stubs/dap/bt.pyi
gdb-stubs/dap/disassemble.pyi
gdb-stubs/dap/evaluate.pyi
gdb-stubs/dap/events.pyi
gdb-stubs/dap/frames.pyi
gdb-stubs/dap/io.pyi
gdb-stubs/dap/launch.pyi
gdb-stubs/dap/locations.pyi
gdb-stubs/dap/memory.pyi
gdb-stubs/dap/modules.pyi
gdb-stubs/dap/next.pyi
gdb-stubs/dap/pause.pyi
gdb-stubs/dap/scopes.pyi
gdb-stubs/dap/server.pyi
gdb-stubs/dap/sources.pyi
gdb-stubs/dap/startup.pyi
gdb-stubs/dap/state.pyi
gdb-stubs/dap/threads.pyi
gdb-stubs/dap/typecheck.pyi
gdb-stubs/dap/varref.pyi
types_gdb-16.3.0.20260109.dist-info/licenses/LICENSE
types_gdb-16.3.0.20260109.dist-info/METADATA
types_gdb-16.3.0.20260109.dist-info/WHEEL
types_gdb-16.3.0.20260109.dist-info/top_level.txt
types_gdb-16.3.0.20260109.dist-info/RECORD
